chachacha/__init__.py
chachacha/configuration.py
chachacha/drivers/__init__.py
chachacha/drivers/git_provider.py
chachacha/drivers/kac.py
chachacha/main.py
chachacha-0.3.1.dist-info/METADATA
chachacha-0.3.1.dist-info/WHEEL
chachacha-0.3.1.dist-info/entry_points.txt
chachacha-0.3.1.dist-info/RECORD
