Metadata-Version: 2.1
Name: chachacha
Version: 0.3.1
Summary: Chachacha changes changelogs
Home-page: https://github.com/aogier/chachacha
License: BSD
Author: Alessandro Ogier
Author-email: alessandro.ogier@gmail.com
Requires-Python: >=3.8,<4.0
Classifier: Development Status :: 3 - Alpha
Classifier: Environment :: Web Environment
Classifier: Intended Audience :: Developers
Classifier: License :: OSI Approved :: BSD License
Classifier: License :: Other/Proprietary License
Classifier: Operating System :: OS Independent
Classifier: Programming Language :: Python :: 3
Classifier: Programming Language :: Python :: 3.8
Classifier: Programming Language :: Python :: 3.9
Classifier: Programming Language :: Python :: 3.10
Classifier: Programming Language :: Python :: 3.11
Classifier: Programming Language :: Python :: 3.7
Classifier: Topic :: Internet :: WWW/HTTP
Requires-Dist: click (>=8.1.0,<9.0.0)
Requires-Dist: jinja2 (>=3.1.0,<4.0.0)
Requires-Dist: keepachangelog (>=0.3.1,<0.4.0)
Requires-Dist: semver (>=3.0.0,<4.0.0)
Project-URL: Repository, https://github.com/aogier/chachacha
